blender_chemicals/__init__.py
blender_chemicals/atoms.json
blender_chemicals/draw.py
blender_chemicals/parse.py
blender_chemicals/run.py
blender_chemicals-0.3.0.dist-info/LICENSE.txt
blender_chemicals-0.3.0.dist-info/METADATA
blender_chemicals-0.3.0.dist-info/WHEEL
blender_chemicals-0.3.0.dist-info/entry_points.txt
blender_chemicals-0.3.0.dist-info/top_level.txt
blender_chemicals-0.3.0.dist-info/RECORD
