Metadata-Version: 2.1
Name: blender-chemicals
Version: 0.3.0
Summary: Imports chemicals into blender with open babel.
Home-page: http://github.com/patrickfuller/blender-chemicals/
Author: Patrick Fuller
Author-email: patrickfuller@gmail.com
License: UNKNOWN
Platform: UNKNOWN
Classifier: Development Status :: 4 - Beta
Classifier: Natural Language :: English
Classifier: Programming Language :: Python
Classifier: Programming Language :: Python :: 3
Classifier: Topic :: Scientific/Engineering :: Chemistry
